LICENSE
pyiseers/__init__.py
pyiseers/pyiseers.py
pyise_ers-0.3.0.3.dist-info/LICENSE
pyise_ers-0.3.0.3.dist-info/METADATA
pyise_ers-0.3.0.3.dist-info/WHEEL
pyise_ers-0.3.0.3.dist-info/RECORD
