Metadata-Version: 2.1
Name: pyise-ers
Version: 0.3.0.3
Summary: Python wrapper for Cisco ISE ERS API
Keywords: poetry
Author: Andreas Falk
Author-email: falk@mockel.se
Requires-Python: >=3.10,<4.0
Classifier: Development Status :: 5 - Production/Stable
Classifier: Environment :: Console
Classifier: Intended Audience :: Developers
Classifier: License :: OSI Approved :: GNU General Public License v2 (GPLv2)
Classifier: Programming Language :: Python
Classifier: Programming Language :: Python :: 3
Classifier: Programming Language :: Python :: 3.10
Classifier: Programming Language :: Python :: 3.11
Classifier: Topic :: System :: Networking
Classifier: Topic :: Utilities
Requires-Dist: furl (>=2.1.3,<3.0.0)
Requires-Dist: requests (>=2.31.0,<3.0.0)
